llmgen/__init__.py
llmgen/_func_parse.py
llmgen/_openai.py
llmgen-0.4.0.dist-info/METADATA
llmgen-0.4.0.dist-info/WHEEL
llmgen-0.4.0.dist-info/RECORD
